Workbook
Name Slicer_Category: #N/A

Sheet Raw_Data
A1: Saas R&D FP&A Model - Monthly Actuals Data
A2: Source: ERP System Export │ Last Updated: June 2026 │ Units: USD
A3: Category | B3: Department | C3: Jan-26 | D3: Feb-26 | E3: Mar-26 | F3: Apr-26 | G3: May-26 | H3: Jun-26 | I3: Jul-26 | J3: Aug-26 | K3: Sep-26 | L3: Oct-26 | M3: Nov-26 | N3: Dec-26
A4: Compensation & Benefits | B4: Software Engineering | C4: 420000 | D4: 432000 | E4: 428000 | F4: 445000 | G4: 451000 | H4: 448000 | I4: 460000 | J4: 455000 | K4: 463000 | L4: 471000 | M4: 468000 | N4: 475000
A5: Compensation & Benefits | B5: Data & ML Engineering | C5: 185000 | D5: 188000 | E5: 191000 | F5: 195000 | G5: 198000 | H5: 201000 | I5: 205000 | J5: 202000 | K5: 208000 | L5: 211000 | M5: 214000 | N5: 218000
A6: Compensation & Benefits | B6: Product Management | C6: 120000 | D6: 122000 | E6: 124000 | F6: 127000 | G6: 129000 | H6: 131000 | I6: 134000 | J6: 132000 | K6: 135000 | L6: 138000 | M6: 140000 | N6: 143000
A7: Compensation & Benefits | B7: QA & DevOps | C7: 95000 | D7: 97000 | E7: 99000 | F7: 101000 | G7: 103000 | H7: 105000 | I7: 107000 | J7: 106000 | K7: 109000 | L7: 111000 | M7: 113000 | N7: 115000
A8: Cloud & Infrastructure | B8: AWS / Azure Compute | C8: 68000 | D8: 71000 | E8: 74000 | F8: 77000 | G8: 80000 | H8: 82000 | I8: 85000 | J8: 88000 | K8: 91000 | L8: 93000 | M8: 96000 | N8: 99000
A9: Cloud & Infrastructure | B9: Data Storage & DBs | C9: 28000 | D9: 29000 | E9: 30000 | F9: 31000 | G9: 32000 | H9: 33000 | I9: 34000 | J9: 35000 | K9: 36000 | L9: 37000 | M9: 38000 | N9: 39000
A10: Cloud & Infrastructure | B10: Security & Monitoring | C10: 18000 | D10: 18500 | E10: 19000 | F10: 19500 | G10: 20000 | H10: 20500 | I10: 21000 | J10: 21500 | K10: 22000 | L10: 22500 | M10: 23000 | N10: 23500
A11: Software & Licenses | B11: Dev Tools (Github, Jira) | C11: 12000 | D11: 12000 | E11: 12500 | F11: 12500 | G11: 13000 | H11: 13000 | I11: 13500 | J11: 13500 | K11: 14000 | L11: 14000 | M11: 14500 | N11: 14500
A12: Software & Licenses | B12: AI/ML Platforms | C12: 22000 | D12: 23000 | E12: 24000 | F12: 25000 | G12: 26000 | H12: 27000 | I12: 28000 | J12: 29000 | K12: 30000 | L12: 31000 | M12: 32000 | N12: 33000
A13: Contracts & Vendors | B13: External Dev Contractors | C13: 55000 | D13: 60000 | E13: 48000 | F13: 52000 | G13: 58000 | H13: 61000 | I13: 45000 | J13: 50000 | K13: 54000 | L13: 57000 | M13: 62000 | N13: 65000
A14: Contracts & Vendors | B14: Research & Partnerships | C14: 15000 | D14: 15000 | E14: 20000 | F14: 15000 | G14: 15000 | H14: 20000 | I14: 15000 | J14: 15000 | K14: 20000 | L14: 15000 | M14: 15000 | N14: 20000
A15: Other R&D Expenses | B15: Travel & Conferences | C15: 8000 | D15: 2000 | E15: 4000 | F15: 18000 | G15: 3000 | H15: 6000 | I15: 22000 | J15: 2000 | K15: 5000 | L15: 15000 | M15: 3000 | N15: 8000
... A17: Other R&D Expenses | B17: Equipment & Hardware | C17: 14000 | D17: 5000 | E17: 8000 | F17: 11000 | G17: 6000 | H17: 9000 | I17: 13000 | J17: 7000 | K17: 10000 | L17: 12000 | M17: 8000 | N17: 16000
A18: TOTAL ACTUALS | C18: =SUM(C4:C17) -> 1066000 | D18: =SUM(D4:D17) -> 1081000 | E18: =SUM(E4:E17) -> 1088500 | F18: =SUM(F4:F17) -> 1135000 | G18: =SUM(G4:G17) -> 1140500 | H18: =SUM(H4:H17) -> 1163500 | I18: =SUM(I4:I17) -> 1188500 | J18: =SUM(J4:J17) -> 1162500 | ... N18: =SUM(N4:N17) -> 1276000

Sheet Pivot_Analysis
B1: ACTUALS BY CATEGORY AND DEPARTMENT - FY2026
A3: Category | B3: Sum of Jan-26 | C3: Sum of Feb-26 | D3: Sum of Mar-26 | E3: Sum of Apr-26 | F3: Sum of May-26 | G3: Sum of Jun-26 | H3: Sum of Jul-26 | I3: Sum of Aug-26 | J3: Sum of Sep-26 | K3: Sum of Oct-26 | L3: Sum of Nov-26 | M3: Sum of Dec-26
A4: Cloud & Infrastructure | B4: 114000 | C4: 118500 | D4: 123000 | E4: 127500 | F4: 132000 | G4: 135500 | H4: 140000 | I4: 144500 | J4: 149000 | K4: 152500 | L4: 157000 | M4: 161500
A5: AWS / Azure Compute | B5: 68000 | C5: 71000 | D5: 74000 | E5: 77000 | F5: 80000 | G5: 82000 | H5: 85000 | I5: 88000 | J5: 91000 | K5: 93000 | L5: 96000 | M5: 99000
A6: Data Storage & DBs | B6: 28000 | C6: 29000 | D6: 30000 | E6: 31000 | F6: 32000 | G6: 33000 | H6: 34000 | I6: 35000 | J6: 36000 | K6: 37000 | L6: 38000 | M6: 39000
A7: Security & Monitoring | B7: 18000 | C7: 18500 | D7: 19000 | E7: 19500 | F7: 20000 | G7: 20500 | H7: 21000 | I7: 21500 | J7: 22000 | K7: 22500 | L7: 23000 | M7: 23500
A8: Compensation & Benefits | B8: 820000 | C8: 839000 | D8: 842000 | E8: 868000 | F8: 881000 | G8: 885000 | H8: 906000 | I8: 895000 | J8: 915000 | K8: 931000 | L8: 935000 | M8: 951000
A9: Data & ML Engineering | B9: 185000 | C9: 188000 | D9: 191000 | E9: 195000 | F9: 198000 | G9: 201000 | H9: 205000 | I9: 202000 | J9: 208000 | K9: 211000 | L9: 214000 | M9: 218000
A10: Product Management | B10: 120000 | C10: 122000 | D10: 124000 | E10: 127000 | F10: 129000 | G10: 131000 | H10: 134000 | I10: 132000 | J10: 135000 | K10: 138000 | L10: 140000 | M10: 143000
A11: QA & DevOps | B11: 95000 | C11: 97000 | D11: 99000 | E11: 101000 | F11: 103000 | G11: 105000 | H11: 107000 | I11: 106000 | J11: 109000 | K11: 111000 | L11: 113000 | M11: 115000
A12: Software Engineering | B12: 420000 | C12: 432000 | D12: 428000 | E12: 445000 | F12: 451000 | G12: 448000 | H12: 460000 | I12: 455000 | J12: 463000 | K12: 471000 | L12: 468000 | M12: 475000
A13: Contracts & Vendors | B13: 70000 | C13: 75000 | D13: 68000 | E13: 67000 | F13: 73000 | G13: 81000 | H13: 60000 | I13: 65000 | J13: 74000 | K13: 72000 | L13: 77000 | M13: 85000
A14: External Dev Contractors | B14: 55000 | C14: 60000 | D14: 48000 | E14: 52000 | F14: 58000 | G14: 61000 | H14: 45000 | I14: 50000 | J14: 54000 | K14: 57000 | L14: 62000 | M14: 65000
A15: Research & Partnerships | B15: 15000 | C15: 15000 | D15: 20000 | E15: 15000 | F15: 15000 | G15: 20000 | H15: 15000 | I15: 15000 | J15: 20000 | K15: 15000 | L15: 15000 | M15: 20000
... A25: Grand Total | B25: 2132000 | C25: 2162000 | D25: 2177000 | E25: 2270000 | F25: 2281000 | G25: 2327000 | H25: 2377000 | I25: 2325000 | J25: 2408000 | K25: 2467000 | L25: 2466000 | M25: 2552000

Sheet Budget
A1: Saas R&D FP&A Model - Annual Budget Plan (FY2026)
A2: Source: ERP System Export │ Last Updated: Dec 2025 │ Units: USD
A3: Category | B3: Department | C3: Jan-26 | D3: Feb-26 | E3: Mar-26 | F3: Apr-26 | G3: May-26 | H3: Jun-26 | I3: Jul-26 | J3: Aug-26 | K3: Sep-26 | L3: Oct-26 | M3: Nov-26 | N3: Dec-26 | O3: FY 2026 Total
A4: Compensation & Benefits | B4: Software Engineering | C4: 415000 | D4: 415000 | E4: 425000 | F4: 440000 | G4: 440000 | H4: 450000 | I4: 455000 | J4: 455000 | K4: 460000 | L4: 465000 | M4: 465000 | N4: 470000 | O4: =SUM(C4:N4) -> 5355000
A5: Compensation & Benefits | B5: Data & ML Engineering | C5: 183000 | D5: 183000 | E5: 190000 | F5: 193000 | G5: 193000 | H5: 200000 | I5: 203000 | J5: 203000 | K5: 207000 | L5: 210000 | M5: 210000 | N5: 215000 | O5: =SUM(C5:N5) -> 2390000
A6: Compensation & Benefits | B6: Product Management | C6: 118000 | D6: 118000 | E6: 122000 | F6: 125000 | G6: 125000 | H6: 130000 | I6: 132000 | J6: 132000 | K6: 135000 | L6: 137000 | M6: 137000 | N6: 140000 | O6: =SUM(C6:N6) -> 1551000
A7: Compensation & Benefits | B7: QA & DevOps | C7: 93000 | D7: 93000 | E7: 97000 | F7: 100000 | G7: 100000 | H7: 104000 | I7: 106000 | J7: 106000 | K7: 108000 | L7: 110000 | M7: 110000 | N7: 113000 | O7: =SUM(C7:N7) -> 1240000
A8: Cloud & Infrastructure | B8: AWS / Azure Compute | C8: 65000 | D8: 68000 | E8: 71000 | F8: 74000 | G8: 77000 | H8: 80000 | I8: 83000 | J8: 86000 | K8: 89000 | L8: 92000 | M8: 95000 | N8: 98000 | O8: =SUM(C8:N8) -> 978000
A9: Cloud & Infrastructure | B9: Data Storage & DBs | C9: 27000 | D9: 28000 | E9: 29000 | F9: 30000 | G9: 31000 | H9: 32000 | I9: 33000 | J9: 34000 | K9: 35000 | L9: 36000 | M9: 37000 | N9: 38000 | O9: =SUM(C9:N9) -> 390000
A10: Cloud & Infrastructure | B10: Security & Monitoring | C10: 17500 | D10: 18000 | E10: 18500 | F10: 19000 | G10: 19500 | H10: 20000 | I10: 20500 | J10: 21000 | K10: 21500 | L10: 22000 | M10: 22500 | N10: 23000 | O10: =SUM(C10:N10) -> 243000
A11: Software & Licenses | B11: Dev Tools (Github, Jira) | C11: 12000 | D11: 12000 | E11: 12000 | F11: 12500 | G11: 12500 | H11: 13000 | I11: 13000 | J11: 13500 | K11: 13500 | L11: 14000 | M11: 14000 | N11: 14500 | O11: =SUM(C11:N11) -> 156500
A12: Software & Licenses | B12: AI/ML Platforms | C12: 21000 | D12: 22000 | E12: 23000 | F12: 24000 | G12: 25000 | H12: 26000 | I12: 27000 | J12: 28000 | K12: 29000 | L12: 30000 | M12: 31000 | N12: 32000 | O12: =SUM(C12:N12) -> 318000
A13: Contracts & Vendors | B13: External Dev Contractors | C13: 50000 | D13: 50000 | E13: 50000 | F13: 50000 | G13: 55000 | H13: 55000 | I13: 50000 | J13: 50000 | K13: 55000 | L13: 55000 | M13: 60000 | N13: 60000 | O13: =SUM(C13:N13) -> 640000
A14: Contracts & Vendors | B14: Research & Partnerships | C14: 15000 | D14: 15000 | E14: 15000 | F14: 15000 | G14: 15000 | H14: 15000 | I14: 15000 | J14: 15000 | K14: 15000 | L14: 15000 | M14: 15000 | N14: 15000 | O14: =SUM(C14:N14) -> 180000
A15: Other R&D Expenses | B15: Travel & Conferences | C15: 5000 | D15: 5000 | E15: 5000 | F15: 15000 | G15: 5000 | H15: 5000 | I15: 20000 | J15: 5000 | K15: 5000 | L15: 12000 | M15: 5000 | N15: 8000 | O15: =SUM(C15:N15) -> 95000
... A17: Other R&D Expenses | B17: Equipment & Hardware | C17: 10000 | D17: 5000 | E17: 8000 | F17: 10000 | G17: 5000 | H17: 8000 | I17: 10000 | J17: 5000 | K17: 8000 | L17: 10000 | M17: 5000 | N17: 10000 | O17: =SUM(C17:N17) -> 94000
A18: TOTAL BUDGET | C18: =SUM(C4:C17) -> 1037500 | D18: =SUM(D4:D17) -> 1038000 | E18: =SUM(E4:E17) -> 1071500 | F18: =SUM(F4:F17) -> 1113500 | G18: =SUM(G4:G17) -> 1109000 | H18: =SUM(H4:H17) -> 1144000 | I18: =SUM(I4:I17) -> 1173500 | J18: =SUM(J4:J17) -> 1159500 | ... O18: =SUM(O4:O17) -> 13702500

Sheet Variance_Engine
A1: VARIANCE ENGINE - Actuals vs. Budget Analysis
A2: SELECT REPORTING MONTH: | C2: Jun-26
A3: Category | B3: Department | C3: YTD Actuals | D3: YTD Budget | E3: Variance | F3: Var (%) | G3: Status
A4: Compensation & Benefits | B4: Software Engineering | C4: {=IFERROR(SUMPRODUCT((COLUMN(Raw_Data!C4:N4)<=MATCH($C$2,Raw_Data!$C$3:$N$3,0)+2)*Raw_Data!C4:N4),0)} -> 2624000 | D4: {=IFERROR(SUMPRODUCT((COLUMN(Budget!C4:N4)<=MATCH($C$2,Budget!$C$3:$N$3,0)+2)*Budget!C4:N4),0)} -> 2585000 | E4: =D4-C4 -> -39000 | F4: =IFERROR((D4-C4)/D4,0) -> -0.015087041 | G4: =IF(E4>0,IF(F4>0.05,"On Track","Watch"),IF(F4<-0.1,"Over Budget","Watch")) -> Watch
A5: Compensation & Benefits | B5: Data & ML Engineering | C5: {=IFERROR(SUMPRODUCT((COLUMN(Raw_Data!C5:N5)<=MATCH($C$2,Raw_Data!$C$3:$N$3,0)+2)*Raw_Data!C5:N5),0)} -> 1158000 | D5: {=IFERROR(SUMPRODUCT((COLUMN(Budget!C5:N5)<=MATCH($C$2,Budget!$C$3:$N$3,0)+2)*Budget!C5:N5),0)} -> 1142000 | E5: =D5-C5 -> -16000 | F5: =IFERROR((D5-C5)/D5,0) -> -0.014010508 | G5: =IF(E5>0,IF(F5>0.05,"On Track","Watch"),IF(F5<-0.1,"Over Budget","Watch")) -> Watch
A6: Compensation & Benefits | B6: Product Management | C6: {=IFERROR(SUMPRODUCT((COLUMN(Raw_Data!C6:N6)<=MATCH($C$2,Raw_Data!$C$3:$N$3,0)+2)*Raw_Data!C6:N6),0)} -> 753000 | D6: {=IFERROR(SUMPRODUCT((COLUMN(Budget!C6:N6)<=MATCH($C$2,Budget!$C$3:$N$3,0)+2)*Budget!C6:N6),0)} -> 738000 | E6: =D6-C6 -> -15000 | F6: =IFERROR((D6-C6)/D6,0) -> -0.020325203 | G6: =IF(E6>0,IF(F6>0.05,"On Track","Watch"),IF(F6<-0.1,"Over Budget","Watch")) -> Watch
A7: Compensation & Benefits | B7: QA & DevOps | C7: {=IFERROR(SUMPRODUCT((COLUMN(Raw_Data!C7:N7)<=MATCH($C$2,Raw_Data!$C$3:$N$3,0)+2)*Raw_Data!C7:N7),0)} -> 600000 | D7: {=IFERROR(SUMPRODUCT((COLUMN(Budget!C7:N7)<=MATCH($C$2,Budget!$C$3:$N$3,0)+2)*Budget!C7:N7),0)} -> 587000 | E7: =D7-C7 -> -13000 | F7: =IFERROR((D7-C7)/D7,0) -> -0.022146508 | G7: =IF(E7>0,IF(F7>0.05,"On Track","Watch"),IF(F7<-0.1,"Over Budget","Watch")) -> Watch
A8: Cloud & Infrastructure | B8: AWS / Azure Compute | C8: {=IFERROR(SUMPRODUCT((COLUMN(Raw_Data!C8:N8)<=MATCH($C$2,Raw_Data!$C$3:$N$3,0)+2)*Raw_Data!C8:N8),0)} -> 452000 | D8: {=IFERROR(SUMPRODUCT((COLUMN(Budget!C8:N8)<=MATCH($C$2,Budget!$C$3:$N$3,0)+2)*Budget!C8:N8),0)} -> 435000 | E8: =D8-C8 -> -17000 | F8: =IFERROR((D8-C8)/D8,0) -> -0.03908046 | G8: =IF(E8>0,IF(F8>0.05,"On Track","Watch"),IF(F8<-0.1,"Over Budget","Watch")) -> Watch
A9: Cloud & Infrastructure | B9: Data Storage & DBs | C9: {=IFERROR(SUMPRODUCT((COLUMN(Raw_Data!C9:N9)<=MATCH($C$2,Raw_Data!$C$3:$N$3,0)+2)*Raw_Data!C9:N9),0)} -> 183000 | D9: {=IFERROR(SUMPRODUCT((COLUMN(Budget!C9:N9)<=MATCH($C$2,Budget!$C$3:$N$3,0)+2)*Budget!C9:N9),0)} -> 177000 | E9: =D9-C9 -> -6000 | F9: =IFERROR((D9-C9)/D9,0) -> -0.033898305 | G9: =IF(E9>0,IF(F9>0.05,"On Track","Watch"),IF(F9<-0.1,"Over Budget","Watch")) -> Watch
A10: Cloud & Infrastructure | B10: Security & Monitoring | C10: {=IFERROR(SUMPRODUCT((COLUMN(Raw_Data!C10:N10)<=MATCH($C$2,Raw_Data!$C$3:$N$3,0)+2)*Raw_Data!C10:N10),0)} -> 115500 | D10: {=IFERROR(SUMPRODUCT((COLUMN(Budget!C10:N10)<=MATCH($C$2,Budget!$C$3:$N$3,0)+2)*Budget!C10:N10),0)} -> 112500 | E10: =D10-C10 -> -3000 | F10: =IFERROR((D10-C10)/D10,0) -> -0.026666667 | G10: =IF(E10>0,IF(F10>0.05,"On Track","Watch"),IF(F10<-0.1,"Over Budget","Watch")) -> Watch
A11: Software & Licenses | B11: Dev Tools (Github, Jira) | C11: {=IFERROR(SUMPRODUCT((COLUMN(Raw_Data!C11:N11)<=MATCH($C$2,Raw_Data!$C$3:$N$3,0)+2)*Raw_Data!C11:N11),0)} -> 75000 | D11: {=IFERROR(SUMPRODUCT((COLUMN(Budget!C11:N11)<=MATCH($C$2,Budget!$C$3:$N$3,0)+2)*Budget!C11:N11),0)} -> 74000 | E11: =D11-C11 -> -1000 | F11: =IFERROR((D11-C11)/D11,0) -> -0.013513514 | G11: =IF(E11>0,IF(F11>0.05,"On Track","Watch"),IF(F11<-0.1,"Over Budget","Watch")) -> Watch
A12: Software & Licenses | B12: AI/ML Platforms | C12: {=IFERROR(SUMPRODUCT((COLUMN(Raw_Data!C12:N12)<=MATCH($C$2,Raw_Data!$C$3:$N$3,0)+2)*Raw_Data!C12:N12),0)} -> 147000 | D12: {=IFERROR(SUMPRODUCT((COLUMN(Budget!C12:N12)<=MATCH($C$2,Budget!$C$3:$N$3,0)+2)*Budget!C12:N12),0)} -> 141000 | E12: =D12-C12 -> -6000 | F12: =IFERROR((D12-C12)/D12,0) -> -0.042553191 | G12: =IF(E12>0,IF(F12>0.05,"On Track","Watch"),IF(F12<-0.1,"Over Budget","Watch")) -> Watch
A13: Contracts & Vendors | B13: External Dev Contractors | C13: {=IFERROR(SUMPRODUCT((COLUMN(Raw_Data!C13:N13)<=MATCH($C$2,Raw_Data!$C$3:$N$3,0)+2)*Raw_Data!C13:N13),0)} -> 334000 | D13: {=IFERROR(SUMPRODUCT((COLUMN(Budget!C13:N13)<=MATCH($C$2,Budget!$C$3:$N$3,0)+2)*Budget!C13:N13),0)} -> 310000 | E13: =D13-C13 -> -24000 | F13: =IFERROR((D13-C13)/D13,0) -> -0.077419355 | G13: =IF(E13>0,IF(F13>0.05,"On Track","Watch"),IF(F13<-0.1,"Over Budget","Watch")) -> Watch
A14: Contracts & Vendors | B14: Research & Partnerships | C14: {=IFERROR(SUMPRODUCT((COLUMN(Raw_Data!C14:N14)<=MATCH($C$2,Raw_Data!$C$3:$N$3,0)+2)*Raw_Data!C14:N14),0)} -> 100000 | D14: {=IFERROR(SUMPRODUCT((COLUMN(Budget!C14:N14)<=MATCH($C$2,Budget!$C$3:$N$3,0)+2)*Budget!C14:N14),0)} -> 90000 | E14: =D14-C14 -> -10000 | F14: =IFERROR((D14-C14)/D14,0) -> -0.11111111 | G14: =IF(E14>0,IF(F14>0.05,"On Track","Watch"),IF(F14<-0.1,"Over Budget","Watch")) -> Over Budget
A15: Other R&D Expenses | B15: Travel & Conferences | C15: {=IFERROR(SUMPRODUCT((COLUMN(Raw_Data!C15:N15)<=MATCH($C$2,Raw_Data!$C$3:$N$3,0)+2)*Raw_Data!C15:N15),0)} -> 41000 | D15: {=IFERROR(SUMPRODUCT((COLUMN(Budget!C15:N15)<=MATCH($C$2,Budget!$C$3:$N$3,0)+2)*Budget!C15:N15),0)} -> 40000 | E15: =D15-C15 -> -1000 | F15: =IFERROR((D15-C15)/D15,0) -> -0.025 | G15: =IF(E15>0,IF(F15>0.05,"On Track","Watch"),IF(F15<-0.1,"Over Budget","Watch")) -> Watch
... A17: Other R&D Expenses | B17: Equipment & Hardware | C17: {=IFERROR(SUMPRODUCT((COLUMN(Raw_Data!C17:N17)<=MATCH($C$2,Raw_Data!$C$3:$N$3,0)+2)*Raw_Data!C17:N17),0)} -> 53000 | D17: {=IFERROR(SUMPRODUCT((COLUMN(Budget!C17:N17)<=MATCH($C$2,Budget!$C$3:$N$3,0)+2)*Budget!C17:N17),0)} -> 46000 | E17: =D17-C17 -> -7000 | F17: =IFERROR((D17-C17)/D17,0) -> -0.15217391 | G17: =IF(E17>0,IF(F17>0.05,"On Track","Watch"),IF(F17<-0.1,"Over Budget","Watch")) -> Over Budget
A18: TOTAL R&D | C18: =SUM(C4:C17) -> 6674500 | D18: =SUM(D4:D17) -> 6513500 | E18: =SUM(E4:E17) -> -161000 | F18: =IFERROR(E18/D18,0) -> -0.024717894 | G18: =IF(E18>0,"On Track","Over Budget") -> Over Budget

Sheet Executive_Summary
B2: R&D PERFORMANCE FINANCIAL REPORT
B3: =Variance_Engine!C2&" YTD | SaaS R&D Division | Finance & Strategy" -> Jun-26 YTD | SaaS R&D Division | Finance & Strategy
C5: YTD ACTUALS | D5: YTD BUDGET | E5: VARIANCE ($) | F5: VARIANCE (%)
C6: =Variance_Engine!C18 -> 6674500 | D6: =Variance_Engine!D18 -> 6513500 | E6: =Variance_Engine!E18 -> -161000 | F6: =Variance_Engine!F18 -> -0.024717894
B8: SPEND BY CATEGORY -- YTD ACTUALS VS BUDGET
B9: CATEGORY | C9: YTD ACTUALS | D9: YTD BUDGET | E9: VARIANCE ($) | F9: VARIANCE (%)
B10: Compensation & Benefits | C10: =SUMIF(Variance_Engine!$A$4:$A$17,"Compensation & Benefits",Variance_Engine!C$4:C$17) -> 5135000 | D10: =SUMIF(Variance_Engine!$A$4:$A$17,"Compensation & Benefits",Variance_Engine!D$4:D$17) -> 5052000 | E10: =D10-C10 -> -83000 | F10: =IFERROR((D10-C10)/D10,0) -> -0.016429137
B11: Cloud & Infrastructure | C11: =SUMIF(Variance_Engine!$A$4:$A$17,"Cloud & Infrastructure",Variance_Engine!C$4:C$17) -> 750500 | D11: =SUMIF(Variance_Engine!$A$4:$A$17,"Cloud & Infrastructure",Variance_Engine!D$4:D$17) -> 724500 | E11: =D11-C11 -> -26000 | F11: =IFERROR((D11-C11)/D11,0) -> -0.035886818
B12: Software & Licenses | C12: =SUMIF(Variance_Engine!$A$4:$A$17,"Software & Licenses",Variance_Engine!C$4:C$17) -> 222000 | D12: =SUMIF(Variance_Engine!$A$4:$A$17,"Software & Licenses",Variance_Engine!D$4:D$17) -> 215000 | E12: =D12-C12 -> -7000 | F12: =IFERROR((D12-C12)/D12,0) -> -0.03255814
B13: Contracts & Vendors | C13: =SUMIF(Variance_Engine!$A$4:$A$17,"Contracts & Vendors",Variance_Engine!C$4:C$17) -> 434000 | D13: =SUMIF(Variance_Engine!$A$4:$A$17,"Contracts & Vendors",Variance_Engine!D$4:D$17) -> 400000 | E13: =D13-C13 -> -34000 | F13: =IFERROR((D13-C13)/D13,0) -> -0.085
B14: Other R&D Expenses | C14: =SUMIF(Variance_Engine!$A$4:$A$17,"Other R&D Expenses",Variance_Engine!C$4:C$17) -> 133000 | D14: =SUMIF(Variance_Engine!$A$4:$A$17,"Other R&D Expenses",Variance_Engine!D$4:D$17) -> 122000 | E14: =D14-C14 -> -11000 | F14: =IFERROR((D14-C14)/D14,0) -> -0.090163934
B15: TOTAL R&D | C15: =SUM(C10:C14) -> 6674500 | D15: =SUM(D10:D14) -> 6513500 | E15: =D15-C15 -> -161000 | F15: =IFERROR((D15-C15)/D15,0) -> -0.024717894
B17: KEY OBSERVATIONS & COMMENTS
B18: GENERAL OUTLOOK | D18: There is a clear overbudget tendency in all the categories in the R&D department. Considering that it is only June, the department needs to decrease their expenses or at least justify this difference with the previous budget.
B19: WHAT TO LOOK OUT FOR? | D19: There was a huge increase in software engineering expenses that needs to be addressed for the remainder of the year.
D20: AWS/Azure cloud services costs increased in the year and has to be checked. There isn't many issues with software and licenses as it is the smallest difference.
D21: Contracts and Vendors as well as other expenses have small values but high variance percentage mainly with travel and external contractors costs going high.
B22: RECOMMENDATIONS & SUGGESTIONS | D22: All 4 areas besides software and licenses have increased substantially and a new forecast can be done if the decision is to lower the budget considering that it is only mid-year and that expenses were expected to increase for the next months.
